Neil-1.0.2.dist-info/DESCRIPTION.rst
Neil-1.0.2.dist-info/METADATA
Neil-1.0.2.dist-info/RECORD
Neil-1.0.2.dist-info/WHEEL
Neil-1.0.2.dist-info/entry_points.txt
Neil-1.0.2.dist-info/metadata.json
Neil-1.0.2.dist-info/top_level.txt
neil/__init__.py
neil/main.py
neil/neil.py
