Metadata-Version: 2.0
Name: Neil
Version: 1.0.2
Summary: A utility program to generate boilerplate code/text from templates.
Home-page: https://github.com/juhosa/neil
Author: Juho Salli
Author-email: juho@jsalli.com
License: MIT
Platform: UNKNOWN
Requires-Dist: Click
Requires-Dist: Jinja2
